README.md
setup.py
polarcbo/__init__.py
polarcbo/functional.py
polarcbo/noise.py
polarcbo/objectives.py
polarcbo/scheduler.py
polarcbo/utils.py
polarcbo.egg-info/PKG-INFO
polarcbo.egg-info/SOURCES.txt
polarcbo.egg-info/dependency_links.txt
polarcbo.egg-info/requires.txt
polarcbo.egg-info/top_level.txt
polarcbo/dynamic/__init__.py
polarcbo/dynamic/cbo.py
polarcbo/dynamic/ccbo.py
polarcbo/dynamic/ccbs.py
polarcbo/dynamic/emcbo.py
polarcbo/dynamic/kmeanscbo.py
polarcbo/dynamic/pcbo.py
polarcbo/dynamic/pcbs.py
polarcbo/dynamic/pdyn.py