Metadata-Version: 2.1
Name: polarcbo
Version: 0.1.1
Summary: Python package for Polarized Consensus Based Optimization
Home-page: https://github.com/TimRoith/polarcbo
Author: Tim Roith
Author-email: tim.roith@fau.de
License: UNKNOWN
Platform: UNKNOWN
Classifier: Programming Language :: Python :: 3
Classifier: License :: OSI Approved :: MIT License
Classifier: Operating System :: OS Independent
Requires-Python: >=3.6
